chatassist/__init__.py
chatassist/api.py
chatassist/cli.py
chatassist/conversation.py
chatassist/gui.py
chatassist/utils.py
chatassist-0.1.0.dist-info/LICENSE
chatassist-0.1.0.dist-info/METADATA
chatassist-0.1.0.dist-info/WHEEL
chatassist-0.1.0.dist-info/top_level.txt
chatassist-0.1.0.dist-info/RECORD
