Metadata-Version: 2.1
Name: chatassist
Version: 0.1.0
Summary: A Python library for interacting with OpenAI's ChatGPT API.
Author: Daryoush Alipour
Author-email: Daryoush Alipour <ai.tirotir@gmail.com>
License: MIT
Project-URL: Homepage, https://github.com/tirotir-ir/chatassist
Project-URL: BugTracker, https://github.com/tirotir-ir/chatassist/issues
Project-URL: Documentation, https://github.com/tirotir-ir/chatassist/wiki
Project-URL: SourceCode, https://github.com/tirotir-ir/chatassist
Keywords: chatgpt,openai,api,assistant
Classifier: Programming Language :: Python :: 3
Classifier: License :: OSI Approved :: MIT License
Classifier: Operating System :: OS Independent
Requires-Python: >=3.6
License-File: LICENSE
Requires-Dist: requests
Requires-Dist: argparse
Requires-Dist: tk
